{
    "name": "screen---st7735",
    "files": [
        "screen.cpp",
        "image.cpp",
        "image.ts",
        "screenimage.ts",
        "text.ts",
        "frame.ts",
        "shims.d.ts",
        "fieldeditors.ts",
        "targetoverrides.ts",
        "ns.ts",
        "image.d.ts",
        "pxtparts.json",
        "imagesoverrides.jres",
        "imagesoverrides.ts",
        "font12.jres",
        "jdprotocol.h",
        "arcadegamepad.h",
        "indexedscreen.h",
        "arcadesound.h",
        "jddisplay.h",
        "jddisplay.cpp"
    ],
    "dependencies": {
        "core": "file:../core"
    },
    "additionalFilePath": "../screen",
    "disablesVariants": [
        "mbdal"
    ],
    "palette": [
        "#000000",
        "#ffffff",
        "#ff2121",
        "#ff93c4",
        "#ff8135",
        "#fff609",
        "#249ca3",
        "#78dc52",
        "#003fad",
        "#87f2ff",
        "#8e2ec4",
        "#a4839f",
        "#5c406c",
        "#e5cdc4",
        "#91463d",
        "#000000"
    ]
}
